pyontutils/__init__.py
pyontutils/annotation.py
pyontutils/asyncd.py
pyontutils/auth-config.py
pyontutils/clifun.py
pyontutils/closed_namespaces.py
pyontutils/combinators.py
pyontutils/config.py
pyontutils/core.py
pyontutils/curies.py
pyontutils/googapis.py
pyontutils/graphml_to_ttl.py
pyontutils/hierarchies.py
pyontutils/identity_bnode.py
pyontutils/integration_test_helper.py
pyontutils/iterio.py
pyontutils/johnson.py
pyontutils/make_catalog.py
pyontutils/namespaces.py
pyontutils/necromancy.py
pyontutils/obo_io.py
pyontutils/ontload.py
pyontutils/ontutils.py
pyontutils/overlaps.py
pyontutils/process_fixed.py
pyontutils/qnamefix.py
pyontutils/rdflib_profile.py
pyontutils/scig.py
pyontutils/scigraph.py
pyontutils/scigraph_client.py
pyontutils/scigraph_codegen.py
pyontutils/sheets.py
pyontutils/sneechenator.py
pyontutils/utils.py
pyontutils/utils_extra.py
pyontutils/utils_fast.py
pyontutils-0.1.39.data/data/share/pyontutils/curie_map.yaml
pyontutils-0.1.39.dist-info/licenses/LICENSE
pyontutils-0.1.39.dist-info/METADATA
pyontutils-0.1.39.dist-info/WHEEL
pyontutils-0.1.39.dist-info/entry_points.txt
pyontutils-0.1.39.dist-info/top_level.txt
pyontutils-0.1.39.dist-info/RECORD
