Metadata-Version: 2.4
Name: pyontutils
Version: 0.1.39
Summary: utilities for working with the NIF ontology, SciGraph, and turtle
Home-page: https://github.com/tgbugs/pyontutils
Author: Tom Gillespie
Author-email: tgbugs@gmail.com
License: MIT
Keywords: ontology scigraph rdflib turtle ttl OWL
Classifier: Development Status :: 4 - Beta
Classifier: License :: OSI Approved :: MIT License
Classifier: Programming Language :: Python :: 3.7
Classifier: Programming Language :: Python :: 3.8
Classifier: Programming Language :: Python :: 3.9
Classifier: Programming Language :: Python :: 3.10
Classifier: Programming Language :: Python :: 3.11
Classifier: Programming Language :: Python :: 3.12
Classifier: Programming Language :: Python :: 3.13
Classifier: Programming Language :: Python :: Implementation :: CPython
Classifier: Programming Language :: Python :: Implementation :: PyPy
Classifier: Operating System :: POSIX :: Linux
Classifier: Operating System :: MacOS :: MacOS X
Classifier: Operating System :: Microsoft :: Windows
Requires-Python: >=3.7
License-File: LICENSE
Requires-Dist: augpathlib>=0.0.33
Requires-Dist: clifn
Requires-Dist: colorlog
Requires-Dist: docopt
Requires-Dist: funowl; python_version >= "3.8"
Requires-Dist: gitpython
Requires-Dist: google-api-python-client
Requires-Dist: google-auth-oauthlib
Requires-Dist: htmlfn
Requires-Dist: idlib>=0.0.1.dev22
Requires-Dist: ipython; python_version < "3.7"
Requires-Dist: joblib>=1.1.0
Requires-Dist: lxml
Requires-Dist: nest_asyncio
Requires-Dist: ontquery>=0.2.11
Requires-Dist: orthauth[sxpr]>=0.0.18
Requires-Dist: pyld
Requires-Dist: pyyaml
Requires-Dist: rdflib>=6.2.0
Requires-Dist: requests
Requires-Dist: terminaltables3
Requires-Dist: ttlser>=1.1.6
Provides-Extra: dev
Requires-Dist: pytest-cov; extra == "dev"
Requires-Dist: wheel; extra == "dev"
Provides-Extra: spell
Requires-Dist: hunspell; extra == "spell"
Provides-Extra: test
Requires-Dist: pytest; extra == "test"
Dynamic: author
Dynamic: author-email
Dynamic: classifier
Dynamic: description
Dynamic: description-content-type
Dynamic: home-page
Dynamic: keywords
Dynamic: license
Dynamic: license-file
Dynamic: provides-extra
Dynamic: requires-dist
Dynamic: requires-python
Dynamic: summary
